NHClone/Noob.py
NHClone/__init__.py
NHClone-0.0.4.dist-info/LICENSE
NHClone-0.0.4.dist-info/METADATA
NHClone-0.0.4.dist-info/WHEEL
NHClone-0.0.4.dist-info/entry_points.txt
NHClone-0.0.4.dist-info/top_level.txt
NHClone-0.0.4.dist-info/RECORD
