Metadata-Version: 2.1
Name: NHClone
Version: 0.0.4
Summary: Facebook Old Id Cloning Tool For All
Home-page: https://github.com/mao2116
Author: Md Nayem Sheikh
Author-email: nayeme19@gmail.com
License: MIT
Keywords: fb old id clone ,facebook Old id clone,noob71,noob-hacker,Noob-Hcaker71 tool,Noob-Hcaker71,bomb sms,termux hack,noob hack,Noob tool
Platform: UNKNOWN
Classifier: Development Status :: 4 - Beta
Classifier: Intended Audience :: Developers
Classifier: Topic :: Software Development :: Libraries :: Python Modules
Classifier: License :: OSI Approved :: MIT License
Classifier: Programming Language :: Python :: 2
Classifier: Operating System :: OS Independent
Classifier: Environment :: Console
Requires-Python: >=2.7.18
Requires-Dist: lolcat
Requires-Dist: requests
Requires-Dist: mechanize
